{
 "custom_fields": [
  {
   "_assign": null,
   "_comments": null,
   "_liked_by": null,
   "_user_tags": null,
   "allow_on_submit": 0,
   "bold": 0,
   "collapsible": 0,
   "collapsible_depends_on": null,
   "columns": 0,
   "creation": "2023-07-28 18:52:45.356959",
   "default": null,
   "depends_on": null,
   "description": null,
   "docstatus": 0,
   "dt": "Payment Reminder Invoice",
   "fetch_from": "sales_invoice.invoice_sent_on",
   "fetch_if_empty": 0,
   "fieldname": "invoice_sent_on",
   "fieldtype": "Datetime",
   "hidden": 0,
   "idx": 9,
   "ignore_user_permissions": 0,
   "ignore_xss_filter": 0,
   "in_global_search": 0,
   "in_list_view": 0,
   "in_standard_filter": 0,
   "insert_after": "reminder_level",
   "label": "Invoice sent on",
   "length": 0,
   "modified": "2023-07-28 18:52:45.356959",
   "modified_by": "lars.mueller@libracore.com",
   "name": "Payment Reminder Invoice-invoice_sent_on",
   "no_copy": 0,
   "options": null,
   "owner": "lars.mueller@libracore.com",
   "parent": null,
   "parentfield": null,
   "parenttype": null,
   "permlevel": 0,
   "precision": "",
   "print_hide": 0,
   "print_hide_if_no_value": 0,
   "print_width": null,
   "read_only": 1,
   "report_hide": 0,
   "reqd": 0,
   "search_index": 0,
   "translatable": 0,
   "unique": 0,
   "width": null
  }
 ],
 "custom_perms": [],
 "doctype": "Payment Reminder Invoice",
 "property_setters": [],
 "sync_on_migrate": 1
}